korv
